statfin/__init__.py
statfin/cache.py
statfin/index_entry.py
statfin/px_web_api.py
statfin/query.py
statfin/query_response.py
statfin/rendering.py
statfin/requests.py
statfin/table.py
statfin/table_response.py
statfin/variable.py
statfin-0.4.1.dist-info/METADATA
statfin-0.4.1.dist-info/WHEEL
statfin-0.4.1.dist-info/licenses/LICENSE
statfin-0.4.1.dist-info/RECORD
