Metadata-Version: 2.4
Name: statfin
Version: 0.4.1
Summary: Interface for Finnish statistics databases
Project-URL: Homepage, https://github.com/lippinj/statfin
Project-URL: Issues, https://github.com/lippinj/statfin/issues
Author-email: Joonas Lipping <lippinj@outlook.com>
License: Copyright (c) 2024 Joonas Lipping
License-File: LICENSE
Classifier: License :: OSI Approved :: MIT License
Classifier: Operating System :: OS Independent
Classifier: Programming Language :: Python :: 3
Requires-Python: >=3.10
Requires-Dist: pandas>=2.2
Requires-Dist: requests>=2.32
